FemtoRV/TUTORIALS/FROM_BLINKER_TO_RISCV/Soc/src/csr_unit.v
module csr_unit (
    input  wire        clk,
    input  wire        resetn,
    
    // 当一条指令真正退休时拉高，用来累加 instret。
    input  wire        valid_inst_retired,

    // 这里用 onehot 形式选择最小 CSR 子集中的哪一个 32 位片段。
    input  wire [3:0]  csrId_is,
    output wire [31:0] csr_rdata,

    // 对外导出完整 64 位计数器，便于仿真和统计。
    output wire [63:0] out_cycle,
    output wire [63:0] out_instret
);

    // 当前实现只维护 cycle 和 instret 两组只读 CSR，已经足够支撑软件统计与简单系统调用。
    reg [63:0] cycle;
    reg [63:0] instret;

    always @(posedge clk) begin
        if (!resetn) begin
            cycle <= 64'b0;
            instret <= 64'b0;
        end else begin
            cycle <= cycle + 64'b1;
            if (valid_inst_retired) begin
                instret <= instret + 64'b1;
            end
        end
    end

    // 通过 onehot 选择把 64 位 CSR 拆成上下两个 32 位窗口返回。
    assign csr_rdata =
        (csrId_is[0] ? cycle[31:0]    : 32'b0) |
        (csrId_is[2] ? cycle[63:32]   : 32'b0) |
        (csrId_is[1] ? instret[31:0]  : 32'b0) |
        (csrId_is[3] ? instret[63:32] : 32'b0) ;

    assign out_cycle = cycle;
    assign out_instret = instret;

endmodule

FemtoRV/TUTORIALS/FROM_BLINKER_TO_RISCV/Soc/tb/tb_csr.v
`timescale 1ns/1ps
module tb_csr;
    reg clk;
    reg resetn;
    reg valid_inst_retired;
    reg [3:0] csrId_is;

    wire [31:0] csr_rdata;
    wire [63:0] out_cycle;
    wire [63:0] out_instret;

    csr_unit dut(
        .clk(clk),
        .resetn(resetn),
        .valid_inst_retired(valid_inst_retired),
        .csrId_is(csrId_is),
        .csr_rdata(csr_rdata),
        .out_cycle(out_cycle),
        .out_instret(out_instret)
    );

    initial begin
        clk = 0;
        forever #5 clk = ~clk;
    end

    initial begin
        $dumpfile("csr.vcd");
        $dumpvars(0, tb_csr);

        resetn = 0;
        valid_inst_retired = 0;
        csrId_is = 0;

        #15;
        resetn = 1; // Unreset at t=15
        
        #10;
        if (out_cycle !== 1 || out_instret !== 0) $display("FAIL: init cycle=%d instret=%d", out_cycle, out_instret);

        #10; // cycle 2
        valid_inst_retired = 1;
        #10; // cycle 3, instret 1
        valid_inst_retired = 0;
        #10; // cycle 4, instret 1

        if (out_cycle !== 4 || out_instret !== 1) $display("FAIL: inc cycle=%d instret=%d", out_cycle, out_instret);

        // test reads
        csrId_is = 4'b0001; // cycle[31:0]
        #1;
        if (csr_rdata !== 4) $display("FAIL: read cycle[31:0] = %d", csr_rdata);

        csrId_is = 4'b0010; // instret[31:0]
        #1;
        if (csr_rdata !== 1) $display("FAIL: read instret[31:0] = %d", csr_rdata);

        $display("ALL TESTS DONE.");
        $finish;
    end
endmodule

FemtoRV/TUTORIALS/FROM_BLINKER_TO_RISCV/csr.vcd
$date
	Wed Mar 25 17:10:47 2026
$end
$version
	Icarus Verilog
$end
$timescale
	1ps
$end
$scope module tb_csr $end
$var wire 64 ! out_instret [63:0] $end
$var wire 64 " out_cycle [63:0] $end
$var wire 32 # csr_rdata [31:0] $end
$var reg 1 $ clk $end
$var reg 4 % csrId_is [3:0] $end
$var reg 1 & resetn $end
$var reg 1 ' valid_inst_retired $end
$scope module dut $end
$var wire 1 $ clk $end
$var wire 4 ( csrId_is [3:0] $end
$var wire 32 ) csr_rdata [31:0] $end
$var wire 64 * out_cycle [63:0] $end
$var wire 64 + out_instret [63:0] $end
$var wire 1 & resetn $end
$var wire 1 ' valid_inst_retired $end
$var reg 64 , cycle [63:0] $end
$var reg 64 - instret [63:0] $end
$upscope $end
$upscope $end
$enddefinitions $end
#0
$dumpvars
bx -
bx ,
bx +
bx *
b0 )
b0 (
0'
0&
b0 %
0$
b0 #
bx "
bx !
$end
#5000
b0 !
b0 +
b0 -
b0 "
b0 *
b0 ,
1$
#10000
0$
#15000
b1 "
b1 *
b1 ,
1$
1&
#20000
0$
#25000
b10 "
b10 *
b10 ,
1$
#30000
0$
#35000
b1 !
b1 +
b1 -
b11 "
b11 *
b11 ,
1$
1'
#40000
0$
#45000
b100 "
b100 *
b100 ,
1$
0'
#50000
0$
#55000
b101 "
b101 *
b101 ,
b101 #
b101 )
1$
b1 %
b1 (
#56000
b1 #
b1 )
b10 %
b10 (
